django_g/__init__.py
django_g/local.py
django_g/middleware.py
django_g/tests.py
django_g-0.0.2.dist-info/LICENSE
django_g-0.0.2.dist-info/METADATA
django_g-0.0.2.dist-info/WHEEL
django_g-0.0.2.dist-info/top_level.txt
django_g-0.0.2.dist-info/RECORD
